pyProtein/__init__.py
pyProtein/amino_acid_properties.py
pyProtein/protein.py
pyProtein-0.0.2.dist-info/LICENSE
pyProtein-0.0.2.dist-info/METADATA
pyProtein-0.0.2.dist-info/WHEEL
pyProtein-0.0.2.dist-info/top_level.txt
pyProtein-0.0.2.dist-info/RECORD
