Metadata-Version: 2.1
Name: pyProtein
Version: 0.0.2
Summary: package for protein IEP calculation etc.
Home-page: https://github.com/AlexanderSouthan/pyProtein
Author: Alexander Southan
Author-email: alexander.southan@web.de
License: UNKNOWN
Project-URL: Bug Tracker, https://github.com/AlexanderSouthan/pyProtein/issues
Platform: UNKNOWN
Classifier: Programming Language :: Python :: 3
Classifier: License :: OSI Approved :: MIT License
Classifier: Operating System :: OS Independent
Requires-Python: >=3.6
License-File: LICENSE
